{"past":[{"form":"atéigh","person":"base","depend":"indep & dep"},{"form":"atéamar","person":"pl1","depend":"indep & dep"},{"form":"atéadar","person":"pl3","depend":"indep & dep"}],"pastcont":[{"form":"atéadh","person":"base","depend":"indep & dep"},{"form":"atéinn","person":"sg1","depend":"indep & dep"},{"form":"atéiteá","person":"sg2","depend":"indep & dep"},{"form":"atéimis","person":"pl1","depend":"indep & dep"},{"form":"atéidís","person":"pl3","depend":"indep & dep"},{"form":"atéití","person":"auto","depend":"indep & dep"}],"prescont":[{"form":"atéann","person":"base","depend":"indep & dep"},{"form":"atéim","person":"sg1","depend":"indep & dep"},{"form":"atéimid","person":"pl1","depend":"indep & dep"},{"form":"atéitear","person":"auto","depend":"indep & dep"}],"fut":[{"form":"atéifidh","person":"base","depend":"indep & dep"},{"form":"atéifimid","person":"pl1","depend":"indep & dep"},{"form":"atéifear","person":"auto","depend":"indep & dep"}],"cond":[{"form":"atéifeadh","person":"base","depend":"indep & dep"},{"form":"atéifinn","person":"sg1","depend":"indep & dep"},{"form":"atéifeá","person":"sg2","depend":"indep & dep"},{"form":"atéfimis","person":"pl1","depend":"indep & dep"},{"form":"atéifidís","person":"pl3","depend":"indep & dep"},{"form":"atéifí","person":"auto","depend":"indep & dep"}],"pres":[]}
