{"imper":[{"form":"bruithníodh","person":"base","mood":"imper"},{"form":"bruithním","person":"sg1","mood":"imper"},{"form":"bruithnigh","person":"sg2","mood":"imper"},{"form":"bruithnímis","person":"pl1","mood":"imper"},{"form":"bruithnígí","person":"pl2","mood":"imper"},{"form":"bruithnídís","person":"pl3","mood":"imper"},{"form":"bruithnítear","person":"auto","mood":"imper"}],"subj":[{"form":"bruithní","person":"base","mood":"subj"},{"form":"bruithnímid","person":"pl1","mood":"subj"},{"form":"bruithnítear","person":"auto","mood":"subj"}]}
