{"past":[{"form":"prímeáil","person":"base","depend":"indep & dep"},{"form":"prímeálamar","person":"pl1","depend":"indep & dep"},{"form":"prímeáladar","person":"pl3","depend":"indep & dep"},{"form":"prímeáladh","person":"auto","depend":"indep & dep"}],"pastcont":[{"form":"prímeáladh","person":"base","depend":"indep & dep"},{"form":"prímeálainn","person":"sg1","depend":"indep & dep"},{"form":"prímeáilteá","person":"sg2","depend":"indep & dep"},{"form":"prímeálaimis","person":"pl1","depend":"indep & dep"},{"form":"prímeálaidís","person":"pl3","depend":"indep & dep"},{"form":"prímeáiltí","person":"auto","depend":"indep & dep"}],"prescont":[{"form":"prímeálann","person":"base","depend":"indep & dep"},{"form":"prímeálaim","person":"sg1","depend":"indep & dep"},{"form":"prímeálaimid","person":"pl1","depend":"indep & dep"},{"form":"prímeáiltear","person":"auto","depend":"indep & dep"}],"fut":[{"form":"prímeálfaidh","person":"base","depend":"indep & dep"},{"form":"prímeálfaimid","person":"pl1","depend":"indep & dep"},{"form":"prímeálfar","person":"auto","depend":"indep & dep"}],"cond":[{"form":"prímeálfadh","person":"base","depend":"indep & dep"},{"form":"prímeálfainn","person":"sg1","depend":"indep & dep"},{"form":"prímeálfá","person":"sg2","depend":"indep & dep"},{"form":"prímeálfaimis","person":"pl1","depend":"indep & dep"},{"form":"prímeálfaidís","person":"pl3","depend":"indep & dep"},{"form":"prímeálfaí","person":"auto","depend":"indep & dep"}],"pres":[]}
