{"past":[{"form":"soirbhigh","person":"base","depend":"indep & dep"},{"form":"soirbhíomar","person":"pl1","depend":"indep & dep"},{"form":"soirbhíodar","person":"pl3","depend":"indep & dep"},{"form":"soirbhíodh","person":"auto","depend":"indep & dep"}],"pastcont":[{"form":"soirbhíodh","person":"base","depend":"indep & dep"},{"form":"soirbhínn","person":"sg1","depend":"indep & dep"},{"form":"soirbhíteá","person":"sg2","depend":"indep & dep"},{"form":"soirbhímis","person":"pl1","depend":"indep & dep"},{"form":"soirbhídís","person":"pl3","depend":"indep & dep"},{"form":"soirbhítí","person":"auto","depend":"indep & dep"}],"prescont":[{"form":"soirbhíonn","person":"base","depend":"indep & dep"},{"form":"soirbhím","person":"sg1","depend":"indep & dep"},{"form":"soirbhímid","person":"pl1","depend":"indep & dep"},{"form":"soirbhítear","person":"auto","depend":"indep & dep"}],"fut":[{"form":"soirbheoidh","person":"base","depend":"indep & dep"},{"form":"soirbheoimid","person":"pl1","depend":"indep & dep"},{"form":"soirbheofar","person":"auto","depend":"indep & dep"}],"cond":[{"form":"soirbheodh","person":"base","depend":"indep & dep"},{"form":"soirbheoinn","person":"sg1","depend":"indep & dep"},{"form":"soirbheofá","person":"sg2","depend":"indep & dep"},{"form":"soirbheoimis","person":"pl1","depend":"indep & dep"},{"form":"soirbheoidís","person":"pl3","depend":"indep & dep"},{"form":"soirbheofaí","person":"auto","depend":"indep & dep"}],"pres":[]}
