{"imper":[{"form":"spochadh","person":"base","mood":"imper"},{"form":"spochaim","person":"sg1","mood":"imper"},{"form":"spoch","person":"sg2","mood":"imper"},{"form":"spochaimis","person":"pl1","mood":"imper"},{"form":"spochaigí","person":"pl2","mood":"imper"},{"form":"spochaidís","person":"pl3","mood":"imper"},{"form":"spochtar","person":"auto","mood":"imper"}],"subj":[{"form":"spocha","person":"base","mood":"subj"},{"form":"spochaimid","person":"pl1","mood":"subj"},{"form":"spochtar","person":"auto","mood":"subj"}]}
