{"past":[{"form":"urghabh","person":"base","depend":"indep & dep"},{"form":"urghabhamar","person":"pl1","depend":"indep & dep"},{"form":"urghabhadar","person":"pl3","depend":"indep & dep"},{"form":"urghabhadh","person":"auto","depend":"indep & dep"}],"pastcont":[{"form":"urghabhadh","person":"base","depend":"indep & dep"},{"form":"urghabhainn","person":"sg1","depend":"indep & dep"},{"form":"urghabhtá","person":"sg2","depend":"indep & dep"},{"form":"urghabhaimis","person":"pl1","depend":"indep & dep"},{"form":"urghabhaidís","person":"pl3","depend":"indep & dep"},{"form":"urghabhtaí","person":"auto","depend":"indep & dep"}],"prescont":[{"form":"urghabhann","person":"base","depend":"indep & dep"},{"form":"urghabhaim","person":"sg1","depend":"indep & dep"},{"form":"urghabhaimid","person":"pl1","depend":"indep & dep"},{"form":"urghabhtar","person":"auto","depend":"indep & dep"}],"fut":[{"form":"urghabhfaidh","person":"base","depend":"indep & dep"},{"form":"urghabhfaimid","person":"pl1","depend":"indep & dep"},{"form":"urghabhfar","person":"auto","depend":"indep & dep"}],"cond":[{"form":"urghabhfadh","person":"base","depend":"indep & dep"},{"form":"urghabhfainn","person":"sg1","depend":"indep & dep"},{"form":"urghabhfá","person":"sg2","depend":"indep & dep"},{"form":"urghabhfaimis","person":"pl1","depend":"indep & dep"},{"form":"urghabhfaidís","person":"pl3","depend":"indep & dep"},{"form":"urghabhfaí","person":"auto","depend":"indep & dep"}],"pres":[]}
