{"called":"searchWord","payl":["wisconsin","english"],"resp":{"forms":["<div class=\"wordItem\">wisconsin</div>"],"result":[{"eng":"Madison, the capital city of Wisconsin.","ga":"madison ardchathair wisconsin","orig":"madison ardchathair wisconsin","html":"<div class=\"sentence tooltip\" id=0>madison ardchathair wisconsin<span class=\"soundicon\" onclick=\"speakIrish(this);\"></span><span class=\"tooltiptext\">Madison, the capital city of Wisconsin.</span></div>","ponchtml":"<div class=\"sentence tooltip\" id=0>madison ardċaṫair wisconsin<span class=\"soundicon\" onclick=\"speakIrish(this);\"></span><span class=\"tooltiptext\">Madison, the capital city of Wisconsin.</span></div>"}]}}
