{"called":"searchWord","payl":["movement","english"],"resp":{"forms":["<div class=\"wordItem\">movement</div>"],"result":[{"eng":"Freedom of movement within the European Union.","ga":"Saorghluaiseacht laistigh den Aontas Eorpach","orig":"Saorghluaiseacht laistigh den Aontas Eorpach","html":"<div class=\"sentence tooltip\" id=0>Saorghluaiseacht laistigh den Aontas Eorpach<span class=\"soundicon\" onclick=\"speakIrish(this);\"></span><span class=\"tooltiptext\">Freedom of movement within the European Union.</span></div>","ponchtml":"<div class=\"sentence tooltip\" id=0>Saorġluaiseaċt laistiġ den Aontas Eorpaċ<span class=\"soundicon\" onclick=\"speakIrish(this);\"></span><span class=\"tooltiptext\">Freedom of movement within the European Union.</span></div>"},{"eng":"The Irish-language movement.","ga":"Gluaiseacht na Gaeilge","orig":"Gluaiseacht na Gaeilge","html":"<div class=\"sentence tooltip\" id=1>Gluaiseacht na Gaeilge<span class=\"soundicon\" onclick=\"speakIrish(this);\"></span><span class=\"tooltiptext\">The Irish-language movement.</span></div>","ponchtml":"<div class=\"sentence tooltip\" id=1>Gluaiseaċt na Gaeilge<span class=\"soundicon\" onclick=\"speakIrish(this);\"></span><span class=\"tooltiptext\">The Irish-language movement.</span></div>"}]}}
