{"called":"searchWord","payl":["chair","english"],"resp":{"forms":["<div class=\"wordItem\">chair</div>"],"result":[{"eng":"Sit down in this comfortable chair.","ga":"Suigh síos sa chathaoir chompordach seo","orig":"Suigh síos sa chathaoir chompordach seo","html":"<div class=\"sentence tooltip\" id=0>Suigh síos sa chathaoir chompordach seo<span class=\"soundicon\" onclick=\"speakIrish(this);\"></span><span class=\"tooltiptext\">Sit down in this comfortable chair.</span></div>","ponchtml":"<div class=\"sentence tooltip\" id=0>Suiġ síos sa ċaṫaoir ċompordaċ seo<span class=\"soundicon\" onclick=\"speakIrish(this);\"></span><span class=\"tooltiptext\">Sit down in this comfortable chair.</span></div>"},{"eng":"The cat is under the chair.","ga":"Tá an cat faoin chathaoir","orig":"Tá an cat faoin chathaoir","html":"<div class=\"sentence tooltip\" id=1>Tá an cat faoin chathaoir<span class=\"soundicon\" onclick=\"speakIrish(this);\"></span><span class=\"tooltiptext\">The cat is under the chair.</span></div>","ponchtml":"<div class=\"sentence tooltip\" id=1>Tá an cat faoin ċaṫaoir<span class=\"soundicon\" onclick=\"speakIrish(this);\"></span><span class=\"tooltiptext\">The cat is under the chair.</span></div>"},{"eng":"She is sitting in the chair.","ga":"Tá sí ina suí sa chathaoir","orig":"Tá sí ina suí sa chathaoir","html":"<div class=\"sentence tooltip\" id=2>Tá sí ina suí sa chathaoir<span class=\"soundicon\" onclick=\"speakIrish(this);\"></span><span class=\"tooltiptext\">She is sitting in the chair.</span></div>","ponchtml":"<div class=\"sentence tooltip\" id=2>Tá sí ina suí sa ċaṫaoir<span class=\"soundicon\" onclick=\"speakIrish(this);\"></span><span class=\"tooltiptext\">She is sitting in the chair.</span></div>"},{"eng":"Take it off the chair.","ga":"Tóg den chathaoir é","orig":"Tóg den chathaoir é","html":"<div class=\"sentence tooltip\" id=3>Tóg den chathaoir é<span class=\"soundicon\" onclick=\"speakIrish(this);\"></span><span class=\"tooltiptext\">Take it off the chair.</span></div>","ponchtml":"<div class=\"sentence tooltip\" id=3>Tóg den ċaṫaoir é<span class=\"soundicon\" onclick=\"speakIrish(this);\"></span><span class=\"tooltiptext\">Take it off the chair.</span></div>"},{"eng":"There is a chair there.","ga":"Tá cathaoir ansin","orig":"Tá cathaoir ansin","html":"<div class=\"sentence tooltip\" id=4>Tá cathaoir ansin<span class=\"soundicon\" onclick=\"speakIrish(this);\"></span><span class=\"tooltiptext\">There is a chair there.</span></div>","ponchtml":"<div class=\"sentence tooltip\" id=4>Tá caṫaoir ansin<span class=\"soundicon\" onclick=\"speakIrish(this);\"></span><span class=\"tooltiptext\">There is a chair there.</span></div>"}]}}
