{"called":"searchWord","payl":["clean","english"],"resp":{"forms":["<div class=\"wordItem\">clean</div>"],"result":[{"eng":"Put on a clean shirt.","ga":"<span class=\"verb_word\" onclick=\"searchVerb('cuir')\">cuir</span> léine ghlan ort féin","orig":"<span class=\"verb_word\" onclick=\"searchVerb('cuir')\">cuir</span> léine ghlan ort féin","html":"<div class=\"sentence tooltip\" id=0><span class=\"verb_word\" onclick=\"searchVerb('cuir')\">cuir</span> léine ghlan ort féin<span class=\"soundicon\" onclick=\"speakIrish(this);\"></span><span class=\"tooltiptext\">Put on a clean shirt.</span></div>","ponchtml":"<div class=\"sentence tooltip\" id=0><span class=\"verb_word\" onclick=\"searċVerb('cuir')\">cuir</span> léine ġlan ort féin<span class=\"soundicon\" onclick=\"speakIrish(this);\"></span><span class=\"tooltiptext\">Put on a clean shirt.</span></div>"},{"eng":"Along with taking care of the child she had to clean the house.","ga":"fara <span class=\"verb_word\" onclick=\"searchVerb('air')\">aire</span> a thabhairt don leanbh bhí uirthi an teach a ghlanadh","orig":"fara <span class=\"verb_word\" onclick=\"searchVerb('air')\">aire</span> a thabhairt don leanbh bhí uirthi an teach a ghlanadh","html":"<div class=\"sentence tooltip\" id=1>fara <span class=\"verb_word\" onclick=\"searchVerb('air')\">aire</span> a thabhairt don leanbh bhí uirthi an teach a ghlanadh<span class=\"soundicon\" onclick=\"speakIrish(this);\"></span><span class=\"tooltiptext\">Along with taking care of the child she had to clean the house.</span></div>","ponchtml":"<div class=\"sentence tooltip\" id=1>fara <span class=\"verb_word\" onclick=\"searċVerb('air')\">aire</span> a ṫaḃairt don leanḃ ḃí uirṫi an teaċ a ġlanaḋ<span class=\"soundicon\" onclick=\"speakIrish(this);\"></span><span class=\"tooltiptext\">Along with taking care of the child she had to clean the house.</span></div>"}]}}
