{"called":"searchWord","payl":["tagairt","exact"],"resp":{"forms":["<div class=\"wordItem\" onclick=\"searchForm(this.innerText);\">tagairt</div>"],"result":[{"eng":"The author makes a reference to a specific case.","ga":"Déanann an t-údar <span class=\"underline_word\">tagairt</span> do chás ar leith","orig":"Déanann an t-údar tagairt do chás ar leith","html":"<div class=\"sentence tooltip\" id=0>Déanann an t-údar <span class=\"underline_word\">tagairt</span> do chás ar leith<span class=\"soundicon\" onclick=\"speakIrish(this);\"></span><span class=\"tooltiptext\">The author makes a reference to a specific case.</span></div>","ponchtml":"<div class=\"sentence tooltip\" id=0>Déanann an t-údar <span class=\"underline_word\">tagairt</span> do ċás ar leiṫ<span class=\"soundicon\" onclick=\"speakIrish(this);\"></span><span class=\"tooltiptext\">The author makes a reference to a specific case.</span></div>"}]}}
