{"called":"searchWord","payl":["inchurtha","exact"],"resp":{"forms":["<div class=\"wordItem\" onclick=\"searchForm(this.innerText);\">inchurtha</div>"],"result":[{"eng":"You're just like him!","ga":"Tá tusa <span class=\"underline_word\">inchurtha</span> leis féin","orig":"Tá tusa inchurtha leis féin","html":"<div class=\"sentence tooltip\" id=0>Tá tusa <span class=\"underline_word\">inchurtha</span> leis féin<span class=\"soundicon\" onclick=\"speakIrish(this);\"></span><span class=\"tooltiptext\">You're just like him!</span></div>","ponchtml":"<div class=\"sentence tooltip\" id=0>Tá tusa <span class=\"underline_word\">inċurṫa</span> leis féin<span class=\"soundicon\" onclick=\"speakIrish(this);\"></span><span class=\"tooltiptext\">You're just like him!</span></div>"}]}}
