{"called":"searchWord","payl":["aonair","exact"],"resp":{"forms":["<div class=\"wordItem\" onclick=\"searchForm(this.innerText);\">aonair</div>"],"result":[{"eng":"I'm an only child.","ga":"Is páiste <span class=\"underline_word\">aonair</span> mé","orig":"Is páiste aonair mé","html":"<div class=\"sentence tooltip\" id=0>Is páiste <span class=\"underline_word\">aonair</span> mé<span class=\"soundicon\" onclick=\"speakIrish(this);\"></span><span class=\"tooltiptext\">I'm an only child.</span></div>","ponchtml":"<div class=\"sentence tooltip\" id=0>Is páiste <span class=\"underline_word\">aonair</span> mé<span class=\"soundicon\" onclick=\"speakIrish(this);\"></span><span class=\"tooltiptext\">I'm an only child.</span></div>"},{"eng":"I'm an only child.","ga":"Is páiste <span class=\"underline_word\">aonair</span> mé","orig":"Is páiste aonair mé","html":"<div class=\"sentence tooltip\" id=1>Is páiste <span class=\"underline_word\">aonair</span> mé<span class=\"soundicon\" onclick=\"speakIrish(this);\"></span><span class=\"tooltiptext\">I'm an only child.</span></div>","ponchtml":"<div class=\"sentence tooltip\" id=1>Is páiste <span class=\"underline_word\">aonair</span> mé<span class=\"soundicon\" onclick=\"speakIrish(this);\"></span><span class=\"tooltiptext\">I'm an only child.</span></div>"},{"eng":"I have no brothers or sisters – I'm an only child.","ga":"Níl deartháir ná deirfiúr ar bith agam – is páiste <span class=\"underline_word\">aonair</span> mé","orig":"Níl deartháir ná deirfiúr ar bith agam – is páiste aonair mé","html":"<div class=\"sentence tooltip\" id=2>Níl deartháir ná deirfiúr ar bith agam – is páiste <span class=\"underline_word\">aonair</span> mé<span class=\"soundicon\" onclick=\"speakIrish(this);\"></span><span class=\"tooltiptext\">I have no brothers or sisters – I'm an only child.</span></div>","ponchtml":"<div class=\"sentence tooltip\" id=2>Níl dearṫáir ná deirfiúr ar biṫ agam – is páiste <span class=\"underline_word\">aonair</span> mé<span class=\"soundicon\" onclick=\"speakIrish(this);\"></span><span class=\"tooltiptext\">I have no brothers or sisters – I'm an only child.</span></div>"}]}}
