{"called":"searchWord","payl":["gheall","exact"],"resp":{"forms":["<div class=\"wordItem\" onclick=\"searchForm(this.innerText);\">gheall</div>"],"result":[{"eng":"We were frustrated because of the lack of good dictionaries.","ga":"Bhí frustrachas orainn mar <span class=\"underline_word\">gheall</span> ar an easpa foclóirí maithe","orig":"Bhí frustrachas orainn mar gheall ar an easpa foclóirí maithe","html":"<div class=\"sentence tooltip\" id=0>Bhí frustrachas orainn mar <span class=\"underline_word\">gheall</span> ar an easpa foclóirí maithe<span class=\"soundicon\" onclick=\"speakIrish(this);\"></span><span class=\"tooltiptext\">We were frustrated because of the lack of good dictionaries.</span></div>","ponchtml":"<div class=\"sentence tooltip\" id=0>Ḃí frustraċas orainn mar <span class=\"underline_word\">ġeall</span> ar an easpa foclóirí maiṫe<span class=\"soundicon\" onclick=\"speakIrish(this);\"></span><span class=\"tooltiptext\">We were frustrated because of the lack of good dictionaries.</span></div>"},{"eng":"Because of the bad weather, the tour was cancelled.","ga":"Mar <span class=\"underline_word\">gheall</span> ar an drochaimsir cuireadh an turas ar ceal","orig":"Mar gheall ar an drochaimsir cuireadh an turas ar ceal","html":"<div class=\"sentence tooltip\" id=1>Mar <span class=\"underline_word\">gheall</span> ar an drochaimsir cuireadh an turas ar ceal<span class=\"soundicon\" onclick=\"speakIrish(this);\"></span><span class=\"tooltiptext\">Because of the bad weather, the tour was cancelled.</span></div>","ponchtml":"<div class=\"sentence tooltip\" id=1>Mar <span class=\"underline_word\">ġeall</span> ar an droċaimsir cuireaḋ an turas ar ceal<span class=\"soundicon\" onclick=\"speakIrish(this);\"></span><span class=\"tooltiptext\">Because of the bad weather, the tour was cancelled.</span></div>"},{"eng":"She had promised it to him – she couldn't back out now.","ga":"<span class=\"underline_word\">Gheall</span> sí dó é – ní fhéadfadh sí dul siar air sin anois","orig":"Gheall sí dó é – ní fhéadfadh sí dul siar air sin anois","html":"<div class=\"sentence tooltip\" id=2><span class=\"underline_word\">Gheall</span> sí dó é – ní fhéadfadh sí dul siar air sin anois<span class=\"soundicon\" onclick=\"speakIrish(this);\"></span><span class=\"tooltiptext\">She had promised it to him – she couldn't back out now.</span></div>","ponchtml":"<div class=\"sentence tooltip\" id=2><span class=\"underline_word\">Ġeall</span> sí dó é – ní ḟéadfaḋ sí dul siar air sin anois<span class=\"soundicon\" onclick=\"speakIrish(this);\"></span><span class=\"tooltiptext\">She had promised it to him – she couldn't back out now.</span></div>"}]}}
