{"called":"searchWord","payl":["caointe","exact"],"resp":{"forms":["<div class=\"wordItem\" onclick=\"searchForm(this.innerText);\">caointe</div>"],"result":[{"eng":"Her eyes were red from how much she had been crying.","ga":"Bhí a dhá shúil <span class=\"verb_word\" onclick=\"searchVerb('dearg')\">dearg</span> ar mhéad is a bhí <span class=\"underline_word\">caointe</span> aici","orig":"Bhí a dhá shúil dearg ar mhéad is a bhí caointe aici","html":"<div class=\"sentence tooltip\" id=0>Bhí a dhá shúil <span class=\"verb_word\" onclick=\"searchVerb('dearg')\">dearg</span> ar mhéad is a bhí <span class=\"underline_word\">caointe</span> aici<span class=\"soundicon\" onclick=\"speakIrish(this);\"></span><span class=\"tooltiptext\">Her eyes were red from how much she had been crying.</span></div>","ponchtml":"<div class=\"sentence tooltip\" id=0>Ḃí a ḋá ẛúil <span class=\"verb_word\" onclick=\"searċVerb('dearg')\">dearg</span> ar ṁéad is a ḃí <span class=\"underline_word\">caointe</span> aici<span class=\"soundicon\" onclick=\"speakIrish(this);\"></span><span class=\"tooltiptext\">Her eyes were red from how much she had been crying.</span></div>"}]}}
