{"called":"searchWord","payl":["stásiún","exact"],"resp":{"forms":["<div class=\"wordItem\" onclick=\"searchForm(this.innerText);\">stásiún</div>"],"result":[{"eng":"This television station caters for the whole community.","ga":"Tá an <span class=\"underline_word\">stásiún</span> teilifíse ag freastal ar an phobal uilig","orig":"Tá an stásiún teilifíse ag freastal ar an phobal uilig","html":"<div class=\"sentence tooltip\" id=0>Tá an <span class=\"underline_word\">stásiún</span> teilifíse ag freastal ar an phobal uilig<span class=\"soundicon\" onclick=\"speakIrish(this);\"></span><span class=\"tooltiptext\">This television station caters for the whole community.</span></div>","ponchtml":"<div class=\"sentence tooltip\" id=0>Tá an <span class=\"underline_word\">stásiún</span> teilifíse ag freastal ar an ṗobal uilig<span class=\"soundicon\" onclick=\"speakIrish(this);\"></span><span class=\"tooltiptext\">This television station caters for the whole community.</span></div>"},{"eng":"This radio station has a very small audience.","ga":"Tá lucht éisteachta an-bheag ag an <span class=\"underline_word\">stásiún</span> raidió seo","orig":"Tá lucht éisteachta an-bheag ag an stásiún raidió seo","html":"<div class=\"sentence tooltip\" id=1>Tá lucht éisteachta an-bheag ag an <span class=\"underline_word\">stásiún</span> raidió seo<span class=\"soundicon\" onclick=\"speakIrish(this);\"></span><span class=\"tooltiptext\">This radio station has a very small audience.</span></div>","ponchtml":"<div class=\"sentence tooltip\" id=1>Tá luċt éisteaċta an-ḃeag ag an <span class=\"underline_word\">stásiún</span> raidió seo<span class=\"soundicon\" onclick=\"speakIrish(this);\"></span><span class=\"tooltiptext\">This radio station has a very small audience.</span></div>"}]}}
