{"called":"searchWord","payl":["mhó","exact"],"resp":{"forms":["<div class=\"wordItem\" onclick=\"searchForm(this.innerText);\">mhó</div>"],"result":[{"eng":"A town with more canals than streets.","ga":"Baile ar <span class=\"underline_word\">mhó</span> <span class=\"verb_word\" onclick=\"searchVerb('líon')\">líon</span> na gcanálacha ná <span class=\"verb_word\" onclick=\"searchVerb('líon')\">líon</span> na sráideanna","orig":"Baile ar mhó líon na gcanálacha ná líon na sráideanna","html":"<div class=\"sentence tooltip\" id=0>Baile ar <span class=\"underline_word\">mhó</span> <span class=\"verb_word\" onclick=\"searchVerb('líon')\">líon</span> na gcanálacha ná <span class=\"verb_word\" onclick=\"searchVerb('líon')\">líon</span> na sráideanna<span class=\"soundicon\" onclick=\"speakIrish(this);\"></span><span class=\"tooltiptext\">A town with more canals than streets.</span></div>","ponchtml":"<div class=\"sentence tooltip\" id=0>Baile ar <span class=\"underline_word\">ṁó</span> <span class=\"verb_word\" onclick=\"searċVerb('líon')\">líon</span> na gcanálaċa ná <span class=\"verb_word\" onclick=\"searċVerb('líon')\">líon</span> na sráideanna<span class=\"soundicon\" onclick=\"speakIrish(this);\"></span><span class=\"tooltiptext\">A town with more canals than streets.</span></div>"},{"eng":"She listened. Nothing more could be heard.","ga":"D'éist sí Ní <span class=\"verb_word\" onclick=\"searchVerb('bí')\">raibh</span> <span class=\"verb_word\" onclick=\"searchVerb('nigh')\">ní</span> ba <span class=\"underline_word\">mhó</span> le mothachtáil","orig":"D'éist sí Ní raibh ní ba mhó le mothachtáil","html":"<div class=\"sentence tooltip\" id=1>D'éist sí Ní <span class=\"verb_word\" onclick=\"searchVerb('bí')\">raibh</span> <span class=\"verb_word\" onclick=\"searchVerb('nigh')\">ní</span> ba <span class=\"underline_word\">mhó</span> le mothachtáil<span class=\"soundicon\" onclick=\"speakIrish(this);\"></span><span class=\"tooltiptext\">She listened. Nothing more could be heard.</span></div>","ponchtml":"<div class=\"sentence tooltip\" id=1>D'éist sí Ní <span class=\"verb_word\" onclick=\"searċVerb('bí')\">raiḃ</span> <span class=\"verb_word\" onclick=\"searċVerb('niġ')\">ní</span> ba <span class=\"underline_word\">ṁó</span> le moṫaċtáil<span class=\"soundicon\" onclick=\"speakIrish(this);\"></span><span class=\"tooltiptext\">She listened. Nothing more could be heard.</span></div>"}]}}
