{"called":"searchWord","payl":["gcrann","match"],"resp":{"forms":["<div class=\"wordItem\" onclick=\"searchForm(this.innerText);\">crann</div>","<div class=\"wordItem\" onclick=\"searchForm(this.innerText);\">gcrann</div>","<div class=\"wordItem\" style=\"background-color: rgb(122 122 122);color: #d0d0d0;text-shadow: 1px 1px 1px #2e2e2e;\">chrainn</div>","<div class=\"wordItem\" style=\"background-color: rgb(122 122 122);color: #d0d0d0;text-shadow: 1px 1px 1px #2e2e2e;\">chrann</div>","<div class=\"wordItem\" style=\"background-color: rgb(122 122 122);color: #d0d0d0;text-shadow: 1px 1px 1px #2e2e2e;\">crainn</div>","<div class=\"wordItem\" style=\"background-color: rgb(122 122 122);color: #d0d0d0;text-shadow: 1px 1px 1px #2e2e2e;\">gcrainn</div>"],"result":[{"eng":"Under the shade of the trees.","ga":"faoi scáth na <span class=\"underline_word\">gcrann</span>","orig":"Faoi scáth na gcrann","html":"<div class=\"sentence tooltip\" id=0>faoi scáth na <span class=\"underline_word\">gcrann</span><span class=\"soundicon\" onclick=\"speakIrish(this);\"></span><span class=\"tooltiptext\">Under the shade of the trees.</span></div>","ponchtml":"<div class=\"sentence tooltip\" id=0>faoi scáṫ na <span class=\"underline_word\">gcrann</span><span class=\"soundicon\" onclick=\"speakIrish(this);\"></span><span class=\"tooltiptext\">Under the shade of the trees.</span></div>"}]}}
