{"called":"searchWord","payl":["scairt","match"],"resp":{"forms":["<div class=\"wordItem\" onclick=\"searchForm(this.innerText);\">scairt</div>","<div class=\"wordItem\" style=\"background-color: rgb(122 122 122);color: #d0d0d0;text-shadow: 1px 1px 1px #2e2e2e;\">scairte</div>","<div class=\"wordItem\" style=\"background-color: rgb(122 122 122);color: #d0d0d0;text-shadow: 1px 1px 1px #2e2e2e;\">scairteá</div>","<div class=\"wordItem\" style=\"background-color: rgb(122 122 122);color: #d0d0d0;text-shadow: 1px 1px 1px #2e2e2e;\">scairteacha</div>","<div class=\"wordItem\" style=\"background-color: rgb(122 122 122);color: #d0d0d0;text-shadow: 1px 1px 1px #2e2e2e;\">scairteadar</div>","<div class=\"wordItem\" style=\"background-color: rgb(122 122 122);color: #d0d0d0;text-shadow: 1px 1px 1px #2e2e2e;\">scairteadh</div>","<div class=\"wordItem\" style=\"background-color: rgb(122 122 122);color: #d0d0d0;text-shadow: 1px 1px 1px #2e2e2e;\">scairteamar</div>","<div class=\"wordItem\" style=\"background-color: rgb(122 122 122);color: #d0d0d0;text-shadow: 1px 1px 1px #2e2e2e;\">scairteann</div>","<div class=\"wordItem\" style=\"background-color: rgb(122 122 122);color: #d0d0d0;text-shadow: 1px 1px 1px #2e2e2e;\">scairteanna</div>","<div class=\"wordItem\" style=\"background-color: rgb(122 122 122);color: #d0d0d0;text-shadow: 1px 1px 1px #2e2e2e;\">scairtear</div>","<div class=\"wordItem\" style=\"background-color: rgb(122 122 122);color: #d0d0d0;text-shadow: 1px 1px 1px #2e2e2e;\">scairtfeá</div>","<div class=\"wordItem\" style=\"background-color: rgb(122 122 122);color: #d0d0d0;text-shadow: 1px 1px 1px #2e2e2e;\">scairtfeadh</div>","<div class=\"wordItem\" style=\"background-color: rgb(122 122 122);color: #d0d0d0;text-shadow: 1px 1px 1px #2e2e2e;\">scairtfear</div>","<div class=\"wordItem\" style=\"background-color: rgb(122 122 122);color: #d0d0d0;text-shadow: 1px 1px 1px #2e2e2e;\">scairtfí</div>","<div class=\"wordItem\" style=\"background-color: rgb(122 122 122);color: #d0d0d0;text-shadow: 1px 1px 1px #2e2e2e;\">scairtfidh</div>","<div class=\"wordItem\" style=\"background-color: rgb(122 122 122);color: #d0d0d0;text-shadow: 1px 1px 1px #2e2e2e;\">scairtfidís</div>","<div class=\"wordItem\" style=\"background-color: rgb(122 122 122);color: #d0d0d0;text-shadow: 1px 1px 1px #2e2e2e;\">scairtfimid</div>","<div class=\"wordItem\" style=\"background-color: rgb(122 122 122);color: #d0d0d0;text-shadow: 1px 1px 1px #2e2e2e;\">scairtfimis</div>","<div class=\"wordItem\" style=\"background-color: rgb(122 122 122);color: #d0d0d0;text-shadow: 1px 1px 1px #2e2e2e;\">scairtfinn</div>","<div class=\"wordItem\" style=\"background-color: rgb(122 122 122);color: #d0d0d0;text-shadow: 1px 1px 1px #2e2e2e;\">scairtí</div>","<div class=\"wordItem\" style=\"background-color: rgb(122 122 122);color: #d0d0d0;text-shadow: 1px 1px 1px #2e2e2e;\">scairtidís</div>","<div class=\"wordItem\" style=\"background-color: rgb(122 122 122);color: #d0d0d0;text-shadow: 1px 1px 1px #2e2e2e;\">scairtigí</div>","<div class=\"wordItem\" style=\"background-color: rgb(122 122 122);color: #d0d0d0;text-shadow: 1px 1px 1px #2e2e2e;\">scairtim</div>","<div class=\"wordItem\" style=\"background-color: rgb(122 122 122);color: #d0d0d0;text-shadow: 1px 1px 1px #2e2e2e;\">scairtimid</div>","<div class=\"wordItem\" style=\"background-color: rgb(122 122 122);color: #d0d0d0;text-shadow: 1px 1px 1px #2e2e2e;\">scairtimis</div>","<div class=\"wordItem\" style=\"background-color: rgb(122 122 122);color: #d0d0d0;text-shadow: 1px 1px 1px #2e2e2e;\">scairtinn</div>"],"result":[{"eng":"\"What's wrong with you?\" called Norma-Jean when Rebekka chucked the bowl into the sink.","ga":"cad <span class=\"verb_word\" onclick=\"searchVerb('aslaigh')\">atá</span> cearr leat a <span class=\"underline_word\"><span class=\"verb_word\" onclick=\"searchVerb('scairt')\">scairt</span></span> norma-jean nuair a chaith rebekka an babhla isteach sa doirteal de ráig","orig":"Cad atá cearr leat a scairt Norma-Jean nuair a chaith Rebekka an babhla isteach sa doirteal de ráig","html":"<div class=\"sentence tooltip\" id=0>cad <span class=\"verb_word\" onclick=\"searchVerb('aslaigh')\">atá</span> cearr leat a <span class=\"underline_word\"><span class=\"verb_word\" onclick=\"searchVerb('scairt')\">scairt</span></span> norma-jean nuair a chaith rebekka an babhla isteach sa doirteal de ráig<span class=\"soundicon\" onclick=\"speakIrish(this);\"></span><span class=\"tooltiptext\">\"What's wrong with you?\" called Norma-Jean when Rebekka chucked the bowl into the sink.</span></div>","ponchtml":"<div class=\"sentence tooltip\" id=0>cad <span class=\"verb_word\" onclick=\"searċVerb('aslaiġ')\">atá</span> cearr leat a <span class=\"underline_word\"><span class=\"verb_word\" onclick=\"searċVerb('scairt')\">scairt</span></span> norma-jean nuair a ċaiṫ rebekka an baḃla isteaċ sa doirteal de ráig<span class=\"soundicon\" onclick=\"speakIrish(this);\"></span><span class=\"tooltiptext\">\"What's wrong with you?\" called Norma-Jean when Rebekka chucked the bowl into the sink.</span></div>"}]}}
